mac_core/mac_core.srcs/sources_1/imports/mac-tvla-verification/rtl/mac_core.v
module mac_core # (
    parameter DATA_WIDTH = 32
)(
    input  wire                   clk,
    input  wire                   rst_n,      
    input  wire                   start_i,    // Chuyển FSM từ IDLE sang ACCUMULATE
    input  wire                   done_i,     // Báo hiệu kết thúc chuỗi MAC, chuyển sang WAIT_DONE
    input  wire                   clear_i,    // Xóa thanh ghi tích lũy về 0
    input  wire                   data_en_i,  // Cờ báo hiệu (A, X) hợp lệ để thực hiện cộng dồn
    input  wire [DATA_WIDTH-1:0]  a_i,        // Q15.16
    input  wire [DATA_WIDTH-1:0]  x_i,        // Q15.16
    // Đã loại bỏ b_i
    output wire [DATA_WIDTH-1:0]  y_o,       
    output wire                   valid_o     // Bật mức 1 khi toàn bộ chuỗi đã tính xong
);

    // FSM States
    localparam S_IDLE        = 2'd0;
    localparam S_ACCUMULATE  = 2'd1; // Đổi tên để phản ánh đúng chức năng
    localparam S_WAIT_DONE   = 2'd2;
    
    wire [63:0] mul_full_w;       
    wire [31:0] mul_truncated_w;  
    wire [31:0] mac_sum_w;       
  
    reg [1:0]  state_curr_r;
    reg [1:0]  state_next_r;
    reg [31:0] y_res_r;
    reg        valid_r;

    // 1. CurrentStateGen
    always @(posedge clk or negedge rst_n) begin
        if (!rst_n)
            state_curr_r <= S_IDLE;
        else
            state_curr_r <= state_next_r;
    end

    // 2. NextStateGen
    always @(*) begin
        case (state_curr_r)
            S_IDLE: begin
                if (start_i)
                    state_next_r = S_ACCUMULATE;
                else
                    state_next_r = S_IDLE;
            end
            S_ACCUMULATE: begin
                // Ở trạng thái này, FSM đứng chờ và lặp lại liên tục.
                // Chỉ thoát ra WAIT_DONE khi có tín hiệu done_i.
                if (done_i)
                    state_next_r = S_WAIT_DONE;
                else
                    state_next_r = S_ACCUMULATE;
            end
            S_WAIT_DONE: begin
                // Thoát về IDLE khi hạ cờ done_i xuống 0
                if (!done_i)
                    state_next_r = S_IDLE;
                else
                    state_next_r = S_WAIT_DONE;
            end
            default: state_next_r = S_IDLE;
        endcase
    end

    // 3. Multiply Logic & Hồi tiếp (Feedback)
    assign mul_full_w      = $signed(a_i) * $signed(x_i);           // Q15.16 * Q15.16 = Q30.32
    assign mul_truncated_w = mul_full_w[47:16];                     
    
    // ĐIỂM CỐT LÕI: Lấy y_res_r cộng ngược trở lại
    assign mac_sum_w       = mul_truncated_w + y_res_r;             

    assign y_o             = y_res_r;
    assign valid_o         = valid_r;

    // 4. OutputGen
    always @(posedge clk or negedge rst_n) begin
        if (!rst_n) begin
            y_res_r <= 32'sd0;
            valid_r <= 1'b0;
        end 
        else if (clear_i) begin
            // Xóa thanh ghi trước khi chạy 1 lượt tính MAC mới
            y_res_r <= 32'sd0;
            valid_r <= 1'b0;
        end
        else begin
            case (state_curr_r)
                S_IDLE: begin
                    valid_r <= 1'b0;
                    y_res_r <= y_res_r; // Giữ nguyên kết quả cũ
                end
                S_ACCUMULATE: begin
                    // CHỈ lật bit thanh ghi (cộng dồn) nếu có tín hiệu data_en_i
                    if (data_en_i) begin
                        y_res_r <= mac_sum_w;
                    end
                    valid_r <= 1'b0; // Đang tính toán chuỗi, chưa xuất kết quả cuối cùng
                end
                S_WAIT_DONE: begin
                    valid_r <= 1'b1;    // Báo hiệu kết quả y_o đã sẵn sàng để đọc
                    y_res_r <= y_res_r;
                end
                default: begin
                    valid_r <= 1'b0;
                    y_res_r <= 32'sd0;
                end
            endcase
        end
    end

endmodule

tb/tb_mac_core.v
`timescale 1ns / 1ps

module tb_mac_core();

    // 1. Khai báo các tham số và tín hiệu
    parameter DATA_WIDTH = 32;
    parameter NUM_TESTS  = 1000; // Số lần cộng dồn trong 1 chuỗi TVLA

    reg                   clk;
    reg                   rst_n;
    reg                   start_i;
    reg                   done_i;
    reg                   clear_i;
    reg                   data_en_i;
    reg  [DATA_WIDTH-1:0] a_i;
    reg  [DATA_WIDTH-1:0] x_i;
    
    wire [DATA_WIDTH-1:0] y_o;
    wire                  valid_o;

    // 2. Khởi tạo Module (Device Under Test - DUT)
    mac_core #(
        .DATA_WIDTH(DATA_WIDTH)
    ) dut (
        .clk        (clk),
        .rst_n      (rst_n),
        .start_i    (start_i),
        .done_i     (done_i),
        .clear_i    (clear_i),
        .data_en_i  (data_en_i),
        .a_i        (a_i),
        .x_i        (x_i),
        .y_o        (y_o),
        .valid_o    (valid_o)
    );

    // 3. Tạo Clock (Tần số 100MHz -> Chu kỳ 10ns)
    initial begin
        clk = 0;
        forever #5 clk = ~clk;
    end

    // 4. Khởi tạo lệnh xuất file VCD cho TVLA
    initial begin
        $dumpfile("tvla_mac_core.vcd");
        // Dump toàn bộ tín hiệu của module tb_mac_core và các module con bên trong
        $dumpvars(0, tb_mac_core); 
    end

    // 5. Task chạy 1 chuỗi MAC (Dùng chung cho cả Fixed và Random)
    task run_mac_sequence;
        input is_random; // 0: Dữ liệu Cố định | 1: Dữ liệu Ngẫu nhiên
        integer i;
        begin
            // B1. Xóa thanh ghi tích lũy
            @(negedge clk);
            clear_i = 1;
            @(negedge clk);
            clear_i = 0;

            // B2. Kích hoạt FSM chuyển sang trạng thái ACCUMULATE
            start_i = 1;
            @(negedge clk);
            start_i = 0;

            // B3. Bơm dữ liệu liên tục vào mạch
            for (i = 0; i < NUM_TESTS; i = i + 1) begin
                data_en_i = 1;
                
                if (is_random == 1) begin
                    a_i = $random;
                    x_i = $random;
                end 
                else begin
                    // Dữ liệu cố định: A = 1.0, X = 2.0 (Định dạng Q15.16)
                    a_i = 32'h0001_0000; 
                    x_i = 32'h0002_0000; 
                end
                
                @(negedge clk); // Đợi 1 sườn xuống của clock (để đảm bảo setup time cho sườn lên)
            end

            // B4. Kết thúc chuỗi, báo cho mạch dừng lại
            data_en_i = 0;
            done_i = 1;
            @(negedge clk);
            done_i = 0;

            // B5. Đợi mạch xuất cờ hợp lệ
            wait(valid_o == 1'b1);
            @(negedge clk);
        end
    endtask

    // 6. Kịch bản test chính (Main Flow)
    initial begin
        // Khởi tạo giá trị ban đầu
        rst_n     = 0;
        start_i   = 0;
        done_i    = 0;
        clear_i   = 0;
        data_en_i = 0;
        a_i       = 0;
        x_i       = 0;

        // Reset hệ thống
        #20 rst_n = 1;
        #10;

        $display("==================================================");
        $display("[%0t] BAT DAU TEST TVLA - KHOI MAC CORE", $time);
        
        // --- CHUỖI 1: FIXED DATA (Tập dữ liệu cố định) ---
        $display("[%0t] Dang chay tap du lieu FIXED...", $time);
        run_mac_sequence(0); 
        $display("[%0t] Hoan thanh FIXED. Ket qua Y = %h", $time, y_o);
        
        #50; // Trễ một chút giữa 2 chuỗi để dễ nhìn trên wave

        // --- CHUỖI 2: RANDOM DATA (Tập dữ liệu ngẫu nhiên) ---
        $display("[%0t] Dang chay tap du lieu RANDOM...", $time);
        run_mac_sequence(1);
        $display("[%0t] Hoan thanh RANDOM. Ket qua Y = %h", $time, y_o);
        
        $display("==================================================");
        
        #100;
        $finish; // Kết thúc mô phỏng, đóng file VCD
    end

endmodule

mac_core/mac_core.sim/sim_1/behav/xsim/tvla_mac_core.vcd
$date
   Mon Apr 27 09:54:23 2026
$end

$version
  2025.1.0
  $dumpfile ("tvla_mac_core.vcd") 
$end

$timescale
  1ps
$end

$scope module tb_mac_core $end
$var reg 1 ! clk $end
$var reg 1 " rst_n $end
$var reg 1 # start_i $end
$var reg 1 $ done_i $end
$var reg 1 % clear_i $end
$var reg 1 & data_en_i $end
$var reg 32 ' a_i [31:0] $end
$var reg 32 ( x_i [31:0] $end
$var wire 32 ) y_o [31:0] $end
$var wire 1 * valid_o $end
$scope module dut $end
$var wire 1 + clk $end
$var wire 1 , rst_n $end
$var wire 1 - start_i $end
$var wire 1 . done_i $end
$var wire 1 / clear_i $end
$var wire 1 0 data_en_i $end
$var wire 32 1 a_i [31:0] $end
$var wire 32 2 x_i [31:0] $end
$var wire 32 ) y_o [31:0] $end
$var wire 1 * valid_o $end
$var wire 64 3 mul_full_w [63:0] $end
$var wire 32 4 mul_truncated_w [31:0] $end
$var wire 32 5 mac_sum_w [31:0] $end
$var reg 2 6 state_curr_r [1:0] $end
$var reg 2 7 state_next_r [1:0] $end
$var reg 32 8 y_res_r [31:0] $end
$var reg 1 9 valid_r $end
$upscope $end
$scope task run_mac_sequence $end
$var reg 1 : is_random $end
$var integer 32 ; i [31:0] $end
$upscope $end
$upscope $end
$enddefinitions $end

#0
$dumpvars
0!
0"
0#
0$
0%
0&
b0 '
b0 (
b0 )
0*
0+
0,
0-
0.
0/
00
b0 1
b0 2
b0 3
b0 4
b0 5
b0 6
b0 7
b0 8
09
x:
bx ;
$end

#5000
1!
1+

#10000
0!
0+

#15000
1!
1+

#20000
0!
1"
0+
1,

#25000
1!
1+

#30000
0!
1%
0+
1/
0:

#35000
1!
1+

#40000
0!
1#
0%
0+
1-
0/
b1 7

#45000
1!
1+
b1 6

#50000
0!
0#
1&
b10000000000000000 '
b100000000000000000 (
0+
0-
10
b10000000000000000 1
b100000000000000000 2
b1000000000000000000000000000000000 3
b100000000000000000 4
b100000000000000000 5
b0 ;

#55000
1!
b100000000000000000 )
1+
b1000000000000000000 5
b100000000000000000 8

#60000
0!
0+
b1 ;

#65000
1!
b1000000000000000000 )
1+
b1100000000000000000 5
b1000000000000000000 8

#70000
0!
0+
b10 ;

#75000
1!
b1100000000000000000 )
1+
b10000000000000000000 5
b1100000000000000000 8

#80000
0!
0+
b11 ;

#85000
1!
b10000000000000000000 )
1+
b10100000000000000000 5
b10000000000000000000 8

#90000
0!
0+
b100 ;

#95000
1!
b10100000000000000000 )
1+
b11000000000000000000 5
b10100000000000000000 8

#100000
0!
0+
b101 ;

#105000
1!
b11000000000000000000 )
1+
b11100000000000000000 5
b11000000000000000000 8

#110000
0!
0+
b110 ;

#115000
1!
b11100000000000000000 )
1+
b100000000000000000000 5
b11100000000000000000 8

#120000
0!
0+
b111 ;

#125000
1!
b100000000000000000000 )
1+
b100100000000000000000 5
b100000000000000000000 8

#130000
0!
0+
b1000 ;

#135000
1!
b100100000000000000000 )
1+
b101000000000000000000 5
b100100000000000000000 8

#140000
0!
0+
b1001 ;

#145000
1!
b101000000000000000000 )
1+
b101100000000000000000 5
b101000000000000000000 8

#150000
0!
0+
b1010 ;

#155000
1!
b101100000000000000000 )
1+
b110000000000000000000 5
b101100000000000000000 8

#160000
0!
0+
b1011 ;

#165000
1!
b110000000000000000000 )
1+
b110100000000000000000 5
b110000000000000000000 8

#170000
0!
0+
b1100 ;

#175000
1!
b110100000000000000000 )
1+
b111000000000000000000 5
b110100000000000000000 8

#180000
0!
0+
b1101 ;

#185000
1!
b111000000000000000000 )
1+
b111100000000000000000 5
b111000000000000000000 8

#190000
0!
0+
b1110 ;

#195000
1!
b111100000000000000000 )
1+
b1000000000000000000000 5
b111100000000000000000 8

#200000
0!
0+
b1111 ;

#205000
1!
b1000000000000000000000 )
1+
b1000100000000000000000 5
b1000000000000000000000 8

#210000
0!
0+
b10000 ;

#215000
1!
b1000100000000000000000 )
1+
b1001000000000000000000 5
b1000100000000000000000 8

#220000
0!
0+
b10001 ;

#225000
1!
b1001000000000000000000 )
1+
b1001100000000000000000 5
b1001000000000000000000 8

#230000
0!
0+
b10010 ;

#235000
1!
b1001100000000000000000 )
1+
b1010000000000000000000 5
b1001100000000000000000 8

#240000
0!
0+
b10011 ;

#245000
1!
b1010000000000000000000 )
1+
b1010100000000000000000 5
b1010000000000000000000 8

#250000
0!
0+
b10100 ;

#255000
1!
b1010100000000000000000 )
1+
b1011000000000000000000 5
b1010100000000000000000 8

#260000
0!
0+
b10101 ;

#265000
1!
b1011000000000000000000 )
1+
b1011100000000000000000 5
b1011000000000000000000 8

#270000
0!
0+
b10110 ;

#275000
1!
b1011100000000000000000 )
1+
b1100000000000000000000 5
b1011100000000000000000 8

#280000
0!
0+
b10111 ;

#285000
1!
b1100000000000000000000 )
1+
b1100100000000000000000 5
b1100000000000000000000 8

#290000
0!
0+
b11000 ;

#295000
1!
b1100100000000000000000 )
1+
b1101000000000000000000 5
b1100100000000000000000 8

#300000
0!
0+
b11001 ;

#305000
1!
b1101000000000000000000 )
1+
b1101100000000000000000 5
b1101000000000000000000 8

#310000
0!
0+
b11010 ;

#315000
1!
b1101100000000000000000 )
1+
b1110000000000000000000 5
b1101100000000000000000 8

#320000
0!
0+
b11011 ;

#325000
1!
b1110000000000000000000 )
1+
b1110100000000000000000 5
b1110000000000000000000 8

#330000
0!
0+
b11100 ;

#335000
1!
b1110100000000000000000 )
1+
b1111000000000000000000 5
b1110100000000000000000 8

#340000
0!
0+
b11101 ;

#345000
1!
b1111000000000000000000 )
1+
b1111100000000000000000 5
b1111000000000000000000 8

#350000
0!
0+
b11110 ;

#355000
1!
b1111100000000000000000 )
1+
b10000000000000000000000 5
b1111100000000000000000 8

#360000
0!
0+
b11111 ;

#365000
1!
b10000000000000000000000 )
1+
b10000100000000000000000 5
b10000000000000000000000 8

#370000
0!
0+
b100000 ;

#375000
1!
b10000100000000000000000 )
1+
b10001000000000000000000 5
b10000100000000000000000 8

#380000
0!
0+
b100001 ;

#385000
1!
b10001000000000000000000 )
1+
b10001100000000000000000 5
b10001000000000000000000 8

#390000
0!
0+
b100010 ;

#395000
1!
b10001100000000000000000 )
1+
b10010000000000000000000 5
b10001100000000000000000 8

#400000
0!
0+
b100011 ;

#405000
1!
b10010000000000000000000 )
1+
b10010100000000000000000 5
b10010000000000000000000 8

#410000
0!
0+
b100100 ;

#415000
1!
b10010100000000000000000 )
1+
b10011000000000000000000 5
b10010100000000000000000 8

#420000
0!
0+
b100101 ;

#425000
1!
b10011000000000000000000 )
1+
b10011100000000000000000 5
b10011000000000000000000 8

#430000
0!
0+
b100110 ;

#435000
1!
b10011100000000000000000 )
1+
b10100000000000000000000 5
b10011100000000000000000 8

#440000
0!
0+
b100111 ;

#445000
1!
b10100000000000000000000 )
1+
b10100100000000000000000 5
b10100000000000000000000 8

#450000
0!
0+
b101000 ;

#455000
1!
b10100100000000000000000 )
1+
b10101000000000000000000 5
b10100100000000000000000 8

#460000
0!
0+
b101001 ;

#465000
1!
b10101000000000000000000 )
1+
b10101100000000000000000 5
b10101000000000000000000 8

#470000
0!
0+
b101010 ;

#475000
1!
b10101100000000000000000 )
1+
b10110000000000000000000 5
b10101100000000000000000 8

#480000
0!
0+
b101011 ;

#485000
1!
b10110000000000000000000 )
1+
b10110100000000000000000 5
b10110000000000000000000 8

#490000
0!
0+
b101100 ;

#495000
1!
b10110100000000000000000 )
1+
b10111000000000000000000 5
b10110100000000000000000 8

#500000
0!
0+
b101101 ;

#505000
1!
b10111000000000000000000 )
1+
b10111100000000000000000 5
b10111000000000000000000 8

#510000
0!
0+
b101110 ;

#515000
1!
b10111100000000000000000 )
1+
b11000000000000000000000 5
b10111100000000000000000 8

#520000
0!
0+
b101111 ;

#525000
1!
b11000000000000000000000 )
1+
b11000100000000000000000 5
b11000000000000000000000 8

#530000
0!
0+
b110000 ;

#535000
1!
b11000100000000000000000 )
1+
b11001000000000000000000 5
b11000100000000000000000 8

#540000
0!
0+
b110001 ;

#545000
1!
b11001000000000000000000 )
1+
b11001100000000000000000 5
b11001000000000000000000 8

#550000
0!
0+
b110010 ;

#555000
1!
b11001100000000000000000 )
1+
b11010000000000000000000 5
b11001100000000000000000 8

#560000
0!
0+
b110011 ;

#565000
1!
b11010000000000000000000 )
1+
b11010100000000000000000 5
b11010000000000000000000 8

#570000
0!
0+
b110100 ;

#575000
1!
b11010100000000000000000 )
1+
b11011000000000000000000 5
b11010100000000000000000 8

#580000
0!
0+
b110101 ;

#585000
1!
b11011000000000000000000 )
1+
b11011100000000000000000 5
b11011000000000000000000 8

#590000
0!
0+
b110110 ;

#595000
1!
b11011100000000000000000 )
1+
b11100000000000000000000 5
b11011100000000000000000 8

#600000
0!
0+
b110111 ;

#605000
1!
b11100000000000000000000 )
1+
b11100100000000000000000 5
b11100000000000000000000 8

#610000
0!
0+
b111000 ;

#615000
1!
b11100100000000000000000 )
1+
b11101000000000000000000 5
b11100100000000000000000 8

#620000
0!
0+
b111001 ;

#625000
1!
b11101000000000000000000 )
1+
b11101100000000000000000 5
b11101000000000000000000 8

#630000
0!
0+
b111010 ;

#635000
1!
b11101100000000000000000 )
1+
b11110000000000000000000 5
b11101100000000000000000 8

#640000
0!
0+
b111011 ;

#645000
1!
b11110000000000000000000 )
1+
b11110100000000000000000 5
b11110000000000000000000 8

#650000
0!
0+
b111100 ;

#655000
1!
b11110100000000000000000 )
1+
b11111000000000000000000 5
b11110100000000000000000 8

#660000
0!
0+
b111101 ;

#665000
1!
b11111000000000000000000 )
1+
b11111100000000000000000 5
b11111000000000000000000 8

#670000
0!
0+
b111110 ;

#675000
1!
b11111100000000000000000 )
1+
b100000000000000000000000 5
b11111100000000000000000 8

#680000
0!
0+
b111111 ;

#685000
1!
b100000000000000000000000 )
1+
b100000100000000000000000 5
b100000000000000000000000 8

#690000
0!
0+
b1000000 ;

#695000
1!
b100000100000000000000000 )
1+
b100001000000000000000000 5
b100000100000000000000000 8

#700000
0!
0+
b1000001 ;

#705000
1!
b100001000000000000000000 )
1+
b100001100000000000000000 5
b100001000000000000000000 8

#710000
0!
0+
b1000010 ;

#715000
1!
b100001100000000000000000 )
1+
b100010000000000000000000 5
b100001100000000000000000 8

#720000
0!
0+
b1000011 ;

#725000
1!
b100010000000000000000000 )
1+
b100010100000000000000000 5
b100010000000000000000000 8

#730000
0!
0+
b1000100 ;

#735000
1!
b100010100000000000000000 )
1+
b100011000000000000000000 5
b100010100000000000000000 8

#740000
0!
0+
b1000101 ;

#745000
1!
b100011000000000000000000 )
1+
b100011100000000000000000 5
b100011000000000000000000 8

#750000
0!
0+
b1000110 ;

#755000
1!
b100011100000000000000000 )
1+
b100100000000000000000000 5
b100011100000000000000000 8

#760000
0!
0+
b1000111 ;

#765000
1!
b100100000000000000000000 )
1+
b100100100000000000000000 5
b100100000000000000000000 8

#770000
0!
0+
b1001000 ;

#775000
1!
b100100100000000000000000 )
1+
b100101000000000000000000 5
b100100100000000000000000 8

#780000
0!
0+
b1001001 ;

#785000
1!
b100101000000000000000000 )
1+
b100101100000000000000000 5
b100101000000000000000000 8

#790000
0!
0+
b1001010 ;

#795000
1!
b100101100000000000000000 )
1+
b100110000000000000000000 5
b100101100000000000000000 8

#800000
0!
0+
b1001011 ;

#805000
1!
b100110000000000000000000 )
1+
b100110100000000000000000 5
b100110000000000000000000 8

#810000
0!
0+
b1001100 ;

#815000
1!
b100110100000000000000000 )
1+
b100111000000000000000000 5
b100110100000000000000000 8

#820000
0!
0+
b1001101 ;

#825000
1!
b100111000000000000000000 )
1+
b100111100000000000000000 5
b100111000000000000000000 8

#830000
0!
0+
b1001110 ;

#835000
1!
b100111100000000000000000 )
1+
b101000000000000000000000 5
b100111100000000000000000 8

#840000
0!
0+
b1001111 ;

#845000
1!
b101000000000000000000000 )
1+
b101000100000000000000000 5
b101000000000000000000000 8

#850000
0!
0+
b1010000 ;

#855000
1!
b101000100000000000000000 )
1+
b101001000000000000000000 5
b101000100000000000000000 8

#860000
0!
0+
b1010001 ;

#865000
1!
b101001000000000000000000 )
1+
b101001100000000000000000 5
b101001000000000000000000 8

#870000
0!
0+
b1010010 ;

#875000
1!
b101001100000000000000000 )
1+
b101010000000000000000000 5
b101001100000000000000000 8

#880000
0!
0+
b1010011 ;

#885000
1!
b101010000000000000000000 )
1+
b101010100000000000000000 5
b101010000000000000000000 8

#890000
0!
0+
b1010100 ;

#895000
1!
b101010100000000000000000 )
1+
b101011000000000000000000 5
b101010100000000000000000 8

#900000
0!
0+
b1010101 ;

#905000
1!
b101011000000000000000000 )
1+
b101011100000000000000000 5
b101011000000000000000000 8

#910000
0!
0+
b1010110 ;

#915000
1!
b101011100000000000000000 )
1+
b101100000000000000000000 5
b101011100000000000000000 8

#920000
0!
0+
b1010111 ;

#925000
1!
b101100000000000000000000 )
1+
b101100100000000000000000 5
b101100000000000000000000 8

#930000
0!
0+
b1011000 ;

#935000
1!
b101100100000000000000000 )
1+
b101101000000000000000000 5
b101100100000000000000000 8

#940000
0!
0+
b1011001 ;

#945000
1!
b101101000000000000000000 )
1+
b101101100000000000000000 5
b101101000000000000000000 8

#950000
0!
0+
b1011010 ;

#955000
1!
b101101100000000000000000 )
1+
b101110000000000000000000 5
b101101100000000000000000 8

#960000
0!
0+
b1011011 ;

#965000
1!
b101110000000000000000000 )
1+
b101110100000000000000000 5
b101110000000000000000000 8

#970000
0!
0+
b1011100 ;

#975000
1!
b101110100000000000000000 )
1+
b101111000000000000000000 5
b101110100000000000000000 8

#980000
0!
0+
b1011101 ;

#985000
1!
b101111000000000000000000 )
1+
b101111100000000000000000 5
b101111000000000000000000 8

#990000
0!
0+
b1011110 ;

#995000
1!
b101111100000000000000000 )
1+
b110000000000000000000000 5
b101111100000000000000000 8

#1000000
0!
0+
b1011111 ;

#1005000
1!
b110000000000000000000000 )
1+
b110000100000000000000000 5
b110000000000000000000000 8

#1010000
0!
0+
b1100000 ;

#1015000
1!
b110000100000000000000000 )
1+
b110001000000000000000000 5
b110000100000000000000000 8

#1020000
0!
0+
b1100001 ;

#1025000
1!
b110001000000000000000000 )
1+
b110001100000000000000000 5
b110001000000000000000000 8

#1030000
0!
0+
b1100010 ;

#1035000
1!
b110001100000000000000000 )
1+
b110010000000000000000000 5
b110001100000000000000000 8

#1040000
0!
0+
b1100011 ;

#1045000
1!
b110010000000000000000000 )
1+
b110010100000000000000000 5
b110010000000000000000000 8

#1050000
0!
0+
b1100100 ;

#1055000
1!
b110010100000000000000000 )
1+
b110011000000000000000000 5
b110010100000000000000000 8

#1060000
0!
0+
b1100101 ;

#1065000
1!
b110011000000000000000000 )
1+
b110011100000000000000000 5
b110011000000000000000000 8

#1070000
0!
0+
b1100110 ;

#1075000
1!
b110011100000000000000000 )
1+
b110100000000000000000000 5
b110011100000000000000000 8

#1080000
0!
0+
b1100111 ;

#1085000
1!
b110100000000000000000000 )
1+
b110100100000000000000000 5
b110100000000000000000000 8

#1090000
0!
0+
b1101000 ;

#1095000
1!
b110100100000000000000000 )
1+
b110101000000000000000000 5
b110100100000000000000000 8

#1100000
0!
0+
b1101001 ;

#1105000
1!
b110101000000000000000000 )
1+
b110101100000000000000000 5
b110101000000000000000000 8

#1110000
0!
0+
b1101010 ;

#1115000
1!
b110101100000000000000000 )
1+
b110110000000000000000000 5
b110101100000000000000000 8

#1120000
0!
0+
b1101011 ;

#1125000
1!
b110110000000000000000000 )
1+
b110110100000000000000000 5
b110110000000000000000000 8

#1130000
0!
0+
b1101100 ;

#1135000
1!
b110110100000000000000000 )
1+
b110111000000000000000000 5
b110110100000000000000000 8

#1140000
0!
0+
b1101101 ;

#1145000
1!
b110111000000000000000000 )
1+
b110111100000000000000000 5
b110111000000000000000000 8

#1150000
0!
0+
b1101110 ;

#1155000
1!
b110111100000000000000000 )
1+
b111000000000000000000000 5
b110111100000000000000000 8

#1160000
0!
0+
b1101111 ;

#1165000
1!
b111000000000000000000000 )
1+
b111000100000000000000000 5
b111000000000000000000000 8

#1170000
0!
0+
b1110000 ;

#1175000
1!
b111000100000000000000000 )
1+
b111001000000000000000000 5
b111000100000000000000000 8

#1180000
0!
0+
b1110001 ;

#1185000
1!
b111001000000000000000000 )
1+
b111001100000000000000000 5
b111001000000000000000000 8

#1190000
0!
0+
b1110010 ;

#1195000
1!
b111001100000000000000000 )
1+
b111010000000000000000000 5
b111001100000000000000000 8

#1200000
0!
0+
b1110011 ;

#1205000
1!
b111010000000000000000000 )
1+
b111010100000000000000000 5
b111010000000000000000000 8

#1210000
0!
0+
b1110100 ;

#1215000
1!
b111010100000000000000000 )
1+
b111011000000000000000000 5
b111010100000000000000000 8

#1220000
0!
0+
b1110101 ;

#1225000
1!
b111011000000000000000000 )
1+
b111011100000000000000000 5
b111011000000000000000000 8

#1230000
0!
0+
b1110110 ;

#1235000
1!
b111011100000000000000000 )
1+
b111100000000000000000000 5
b111011100000000000000000 8

#1240000
0!
0+
b1110111 ;

#1245000
1!
b111100000000000000000000 )
1+
b111100100000000000000000 5
b111100000000000000000000 8

#1250000
0!
0+
b1111000 ;

#1255000
1!
b111100100000000000000000 )
1+
b111101000000000000000000 5
b111100100000000000000000 8

#1260000
0!
0+
b1111001 ;

#1265000
1!
b111101000000000000000000 )
1+
b111101100000000000000000 5
b111101000000000000000000 8

#1270000
0!
0+
b1111010 ;

#1275000
1!
b111101100000000000000000 )
1+
b111110000000000000000000 5
b111101100000000000000000 8

#1280000
0!
0+
b1111011 ;

#1285000
1!
b111110000000000000000000 )
1+
b111110100000000000000000 5
b111110000000000000000000 8

#1290000
0!
0+
b1111100 ;

#1295000
1!
b111110100000000000000000 )
1+
b111111000000000000000000 5
b111110100000000000000000 8

#1300000
0!
0+
b1111101 ;

#1305000
1!
b111111000000000000000000 )
1+
b111111100000000000000000 5
b111111000000000000000000 8

#1310000
0!
0+
b1111110 ;

#1315000
1!
b111111100000000000000000 )
1+
b1000000000000000000000000 5
b111111100000000000000000 8

#1320000
0!
0+
b1111111 ;

#1325000
1!
b1000000000000000000000000 )
1+
b1000000100000000000000000 5
b1000000000000000000000000 8

#1330000
0!
0+
b10000000 ;

#1335000
1!
b1000000100000000000000000 )
1+
b1000001000000000000000000 5
b1000000100000000000000000 8

#1340000
0!
0+
b10000001 ;

#1345000
1!
b1000001000000000000000000 )
1+
b1000001100000000000000000 5
b1000001000000000000000000 8

#1350000
0!
0+
b10000010 ;

#1355000
1!
b1000001100000000000000000 )
1+
b1000010000000000000000000 5
b1000001100000000000000000 8

#1360000
0!
0+
b10000011 ;

#1365000
1!
b1000010000000000000000000 )
1+
b1000010100000000000000000 5
b1000010000000000000000000 8

#1370000
0!
0+
b10000100 ;

#1375000
1!
b1000010100000000000000000 )
1+
b1000011000000000000000000 5
b1000010100000000000000000 8

#1380000
0!
0+
b10000101 ;

#1385000
1!
b1000011000000000000000000 )
1+
b1000011100000000000000000 5
b1000011000000000000000000 8

#1390000
0!
0+
b10000110 ;

#1395000
1!
b1000011100000000000000000 )
1+
b1000100000000000000000000 5
b1000011100000000000000000 8

#1400000
0!
0+
b10000111 ;

#1405000
1!
b1000100000000000000000000 )
1+
b1000100100000000000000000 5
b1000100000000000000000000 8

#1410000
0!
0+
b10001000 ;

#1415000
1!
b1000100100000000000000000 )
1+
b1000101000000000000000000 5
b1000100100000000000000000 8

#1420000
0!
0+
b10001001 ;

#1425000
1!
b1000101000000000000000000 )
1+
b1000101100000000000000000 5
b1000101000000000000000000 8

#1430000
0!
0+
b10001010 ;

#1435000
1!
b1000101100000000000000000 )
1+
b1000110000000000000000000 5
b1000101100000000000000000 8

#1440000
0!
0+
b10001011 ;

#1445000
1!
b1000110000000000000000000 )
1+
b1000110100000000000000000 5
b1000110000000000000000000 8

#1450000
0!
0+
b10001100 ;

#1455000
1!
b1000110100000000000000000 )
1+
b1000111000000000000000000 5
b1000110100000000000000000 8

#1460000
0!
0+
b10001101 ;

#1465000
1!
b1000111000000000000000000 )
1+
b1000111100000000000000000 5
b1000111000000000000000000 8

#1470000
0!
0+
b10001110 ;

#1475000
1!
b1000111100000000000000000 )
1+
b1001000000000000000000000 5
b1000111100000000000000000 8

#1480000
0!
0+
b10001111 ;

#1485000
1!
b1001000000000000000000000 )
1+
b1001000100000000000000000 5
b1001000000000000000000000 8

#1490000
0!
0+
b10010000 ;

#1495000
1!
b1001000100000000000000000 )
1+
b1001001000000000000000000 5
b1001000100000000000000000 8

#1500000
0!
0+
b10010001 ;

#1505000
1!
b1001001000000000000000000 )
1+
b1001001100000000000000000 5
b1001001000000000000000000 8

#1510000
0!
0+
b10010010 ;

#1515000
1!
b1001001100000000000000000 )
1+
b1001010000000000000000000 5
b1001001100000000000000000 8

#1520000
0!
0+
b10010011 ;

#1525000
1!
b1001010000000000000000000 )
1+
b1001010100000000000000000 5
b1001010000000000000000000 8

#1530000
0!
0+
b10010100 ;

#1535000
1!
b1001010100000000000000000 )
1+
b1001011000000000000000000 5
b1001010100000000000000000 8

#1540000
0!
0+
b10010101 ;

#1545000
1!
b1001011000000000000000000 )
1+
b1001011100000000000000000 5
b1001011000000000000000000 8

#1550000
0!
0+
b10010110 ;

#1555000
1!
b1001011100000000000000000 )
1+
b1001100000000000000000000 5
b1001011100000000000000000 8

#1560000
0!
0+
b10010111 ;

#1565000
1!
b1001100000000000000000000 )
1+
b1001100100000000000000000 5
b1001100000000000000000000 8

#1570000
0!
0+
b10011000 ;

#1575000
1!
b1001100100000000000000000 )
1+
b1001101000000000000000000 5
b1001100100000000000000000 8

#1580000
0!
0+
b10011001 ;

#1585000
1!
b1001101000000000000000000 )
1+
b1001101100000000000000000 5
b1001101000000000000000000 8

#1590000
0!
0+
b10011010 ;

#1595000
1!
b1001101100000000000000000 )
1+
b1001110000000000000000000 5
b1001101100000000000000000 8

#1600000
0!
0+
b10011011 ;

#1605000
1!
b1001110000000000000000000 )
1+
b1001110100000000000000000 5
b1001110000000000000000000 8

#1610000
0!
0+
b10011100 ;

#1615000
1!
b1001110100000000000000000 )
1+
b1001111000000000000000000 5
b1001110100000000000000000 8

#1620000
0!
0+
b10011101 ;

#1625000
1!
b1001111000000000000000000 )
1+
b1001111100000000000000000 5
b1001111000000000000000000 8

#1630000
0!
0+
b10011110 ;

#1635000
1!
b1001111100000000000000000 )
1+
b1010000000000000000000000 5
b1001111100000000000000000 8

#1640000
0!
0+
b10011111 ;

#1645000
1!
b1010000000000000000000000 )
1+
b1010000100000000000000000 5
b1010000000000000000000000 8

#1650000
0!
0+
b10100000 ;

