mac_core/mac_core.srcs/sources_1/imports/mac-tvla-verification/rtl/mac_core.v
module mac_core # (
    parameter DATA_WIDTH = 32
)(
    input  wire                   clk,
    input  wire                   rst_n,      
    input  wire                   start_i,    // Chuyển FSM từ IDLE sang ACCUMULATE
    input  wire                   done_i,     // Báo hiệu kết thúc chuỗi MAC, chuyển sang WAIT_DONE
    input  wire                   clear_i,    // Xóa thanh ghi tích lũy về 0
    input  wire                   data_en_i,  // Cờ báo hiệu (A, X) hợp lệ để thực hiện cộng dồn
    input  wire [DATA_WIDTH-1:0]  a_i,        // Q15.16
    input  wire [DATA_WIDTH-1:0]  x_i,        // Q15.16
    // Đã loại bỏ b_i
    output wire [DATA_WIDTH-1:0]  y_o,       
    output wire                   valid_o     // Bật mức 1 khi toàn bộ chuỗi đã tính xong
);

    // FSM States
    localparam S_IDLE        = 2'd0;
    localparam S_ACCUMULATE  = 2'd1; // Đổi tên để phản ánh đúng chức năng
    localparam S_WAIT_DONE   = 2'd2;
    
    wire [63:0] mul_full_w;       
    wire [31:0] mul_truncated_w;  
    wire [31:0] mac_sum_w;       
  
    reg [1:0]  state_curr_r;
    reg [1:0]  state_next_r;
    reg [31:0] y_res_r;
    reg        valid_r;

    // 1. CurrentStateGen
    always @(posedge clk or negedge rst_n) begin
        if (!rst_n)
            state_curr_r <= S_IDLE;
        else
            state_curr_r <= state_next_r;
    end

    // 2. NextStateGen
    always @(*) begin
        case (state_curr_r)
            S_IDLE: begin
                if (start_i)
                    state_next_r = S_ACCUMULATE;
                else
                    state_next_r = S_IDLE;
            end
            S_ACCUMULATE: begin
                // Ở trạng thái này, FSM đứng chờ và lặp lại liên tục.
                // Chỉ thoát ra WAIT_DONE khi có tín hiệu done_i.
                if (done_i)
                    state_next_r = S_WAIT_DONE;
                else
                    state_next_r = S_ACCUMULATE;
            end
            S_WAIT_DONE: begin
                // Thoát về IDLE khi hạ cờ done_i xuống 0
                if (!done_i)
                    state_next_r = S_IDLE;
                else
                    state_next_r = S_WAIT_DONE;
            end
            default: state_next_r = S_IDLE;
        endcase
    end

    // 3. Multiply Logic & Hồi tiếp (Feedback)
    assign mul_full_w      = $signed(a_i) * $signed(x_i);           // Q15.16 * Q15.16 = Q30.32
    assign mul_truncated_w = mul_full_w[47:16];                     
    
    // ĐIỂM CỐT LÕI: Lấy y_res_r cộng ngược trở lại
    assign mac_sum_w       = mul_truncated_w + y_res_r;             

    assign y_o             = y_res_r;
    assign valid_o         = valid_r;

    // 4. OutputGen
    always @(posedge clk or negedge rst_n) begin
        if (!rst_n) begin
            y_res_r <= 32'sd0;
            valid_r <= 1'b0;
        end 
        else if (clear_i) begin
            // Xóa thanh ghi trước khi chạy 1 lượt tính MAC mới
            y_res_r <= 32'sd0;
            valid_r <= 1'b0;
        end
        else begin
            case (state_curr_r)
                S_IDLE: begin
                    valid_r <= 1'b0;
                    y_res_r <= y_res_r; // Giữ nguyên kết quả cũ
                end
                S_ACCUMULATE: begin
                    // CHỈ lật bit thanh ghi (cộng dồn) nếu có tín hiệu data_en_i
                    if (data_en_i) begin
                        y_res_r <= mac_sum_w;
                    end
                    valid_r <= 1'b0; // Đang tính toán chuỗi, chưa xuất kết quả cuối cùng
                end
                S_WAIT_DONE: begin
                    valid_r <= 1'b1;    // Báo hiệu kết quả y_o đã sẵn sàng để đọc
                    y_res_r <= y_res_r;
                end
                default: begin
                    valid_r <= 1'b0;
                    y_res_r <= 32'sd0;
                end
            endcase
        end
    end

endmodule

tb/tb_mac_core.v
`timescale 1ns / 1ps

module tb_mac_core();

    // 1. Khai báo các tham số và tín hiệu
    parameter DATA_WIDTH = 32;
    parameter NUM_TESTS  = 2000; // TỔNG SỐ MẪU: 2000 lần tính toán đan xen

    reg                   clk;
    reg                   rst_n;
    reg                   start_i;
    reg                   done_i;
    reg                   clear_i;
    reg                   data_en_i;
    reg  [DATA_WIDTH-1:0] a_i;
    reg  [DATA_WIDTH-1:0] x_i;
    
    wire [DATA_WIDTH-1:0] y_o;
    wire                  valid_o;

    // Biến quản lý file nhãn (Label)
    integer fd;         
    reg current_label;  // 0: Fixed, 1: Random

    // 2. Khởi tạo Module (Device Under Test - DUT)
    mac_core #(
        .DATA_WIDTH(DATA_WIDTH)
    ) dut (
        .clk        (clk),
        .rst_n      (rst_n),
        .start_i    (start_i),
        .done_i     (done_i),
        .clear_i    (clear_i),
        .data_en_i  (data_en_i),
        .a_i        (a_i),
        .x_i        (x_i),
        .y_o        (y_o),
        .valid_o    (valid_o)
    );

    // 3. Tạo Clock (Tần số 100MHz -> Chu kỳ 10ns)
    initial begin
        clk = 0;
        forever #5 clk = ~clk;
    end

    // 4. Khởi tạo lệnh xuất file VCD cho TVLA
    initial begin
        $dumpfile("tvla_mac_core.vcd");
        $dumpvars(0, tb_mac_core); 
    end

    // 5. Task chạy chuỗi MAC ĐAN XEN NGẪU NHIÊN (Interleaved)
    task run_mac_interleaved;
        integer i;
        begin
            // B1. Xóa thanh ghi tích lũy
            @(negedge clk);
            clear_i = 1;
            @(negedge clk);
            clear_i = 0;

            // B2. Kích hoạt FSM chuyển sang trạng thái ACCUMULATE
            start_i = 1;
            @(negedge clk);
            start_i = 0;

            // B3. Nạp dữ liệu 2000 lần
            for (i = 0; i < NUM_TESTS; i = i + 1) begin
                data_en_i = 1;
                
                //  Lấy bit cuối của $random (0 hoặc 1)
                current_label = $random & 1'b1; 
                
                // Ghi nhãn ra file text 
                $fdisplay(fd, "%0d", current_label);
                
                if (current_label == 1'b1) begin
                    // Nhãn 1 -> Dữ liệu Ngẫu nhiên
                    a_i = $random;
                    x_i = $random;
                end 
                else begin
                    // Nhãn 0 -> Dữ liệu Cố định (Corner Cases)
                    a_i = 32'h5555_5555; 
                    x_i = 32'hFFFF_FFFF; 
                end
                
                @(negedge clk); // Đợi 1 sườn xuống
            end

            // B4. Kết thúc chuỗi, báo cho mạch dừng lại
            data_en_i = 0;
            done_i = 1;
            @(negedge clk);
            done_i = 0;

            // B5. Đợi mạch xuất cờ hợp lệ
            wait(valid_o == 1'b1);
            @(negedge clk);
        end
    endtask

    // 6. Kịch bản test chính (Main Flow)
    initial begin
        // Khởi tạo giá trị ban đầu
        rst_n     = 0;
        start_i   = 0;
        done_i    = 0;
        clear_i   = 0;
        data_en_i = 0;
        a_i       = 0;
        x_i       = 0;

        // Reset hệ thống
        #200 rst_n = 1;
        #50;

        $display("==================================================");
        $display("[%0t] BAT DAU TEST TVLA - PHUONG PHAP INTERLEAVED", $time);
        
        // Mở file txt để chuẩn bị ghi nhãn
        fd = $fopen("tvla_labels.txt", "w");
        if (fd == 0) begin
            $display("LOI: Khong the tao file tvla_labels.txt");
            $finish;
        end

        // Gọi Task chạy 2000 mẫu đan xen
        $display("[%0t] Dang bom du lieu va ghi Label...", $time);
        run_mac_interleaved(); 
        
        $display("[%0t] Hoan thanh. Ket qua Y = %h", $time, y_o);
        $display("==================================================");
        
        // Đóng file text
        $fclose(fd);
        
        #100;
        $finish; // Kết thúc mô phỏng
    end

endmodule

mac_core/mac_core.sim/sim_1/behav/xsim/tvla_mac_core.vcd
$date
   Sun May  3 19:40:20 2026
$end

$version
  2025.1.0
  $dumpfile ("tvla_mac_core.vcd") 
$end

$timescale
  1ps
$end

$scope module tb_mac_core $end
$var reg 1 ! clk $end
$var reg 1 " rst_n $end
$var reg 1 # start_i $end
$var reg 1 $ done_i $end
$var reg 1 % clear_i $end
$var reg 1 & data_en_i $end
$var reg 32 ' a_i [31:0] $end
$var reg 32 ( x_i [31:0] $end
$var wire 32 ) y_o [31:0] $end
$var wire 1 * valid_o $end
$var integer 32 + fd [31:0] $end
$var reg 1 , current_label $end
$scope module dut $end
$var wire 1 - clk $end
$var wire 1 . rst_n $end
$var wire 1 / start_i $end
$var wire 1 0 done_i $end
$var wire 1 1 clear_i $end
$var wire 1 2 data_en_i $end
$var wire 32 3 a_i [31:0] $end
$var wire 32 4 x_i [31:0] $end
$var wire 32 ) y_o [31:0] $end
$var wire 1 * valid_o $end
$var wire 64 5 mul_full_w [63:0] $end
$var wire 32 6 mul_truncated_w [31:0] $end
$var wire 32 7 mac_sum_w [31:0] $end
$var reg 2 8 state_curr_r [1:0] $end
$var reg 2 9 state_next_r [1:0] $end
$var reg 32 : y_res_r [31:0] $end
$var reg 1 ; valid_r $end
$upscope $end
$scope task run_mac_interleaved $end
$var integer 32 < i [31:0] $end
$upscope $end
$upscope $end
$enddefinitions $end

#0
$dumpvars
0!
0"
0#
0$
0%
0&
b0 '
b0 (
b0 )
0*
bx +
x,
0-
0.
0/
00
01
02
b0 3
b0 4
b0 5
b0 6
b0 7
b0 8
b0 9
b0 :
0;
bx <
$end

#5000
1!
1-

#10000
0!
0-

#15000
1!
1-

#20000
0!
0-

#25000
1!
1-

#30000
0!
0-

#35000
1!
1-

#40000
0!
0-

#45000
1!
1-

#50000
0!
0-

#55000
1!
1-

#60000
0!
0-

#65000
1!
1-

#70000
0!
0-

#75000
1!
1-

#80000
0!
0-

#85000
1!
1-

#90000
0!
0-

#95000
1!
1-

#100000
0!
0-

#105000
1!
1-

#110000
0!
0-

#115000
1!
1-

#120000
0!
0-

#125000
1!
1-

#130000
0!
0-

#135000
1!
1-

#140000
0!
0-

#145000
1!
1-

#150000
0!
0-

#155000
1!
1-

#160000
0!
0-

#165000
1!
1-

#170000
0!
0-

#175000
1!
1-

#180000
0!
0-

#185000
1!
1-

#190000
0!
0-

#195000
1!
1-

#200000
0!
1"
0-
1.

#205000
1!
1-

#210000
0!
0-

#215000
1!
1-

#220000
0!
0-

#225000
1!
1-

#230000
0!
0-

#235000
1!
1-

#240000
0!
0-

#245000
1!
1-

#250000
0!
1%
b11111111111111111011000111100000 +
0-
11

#255000
1!
1-

#260000
0!
1#
0%
0-
1/
01
b1 9

#265000
1!
1-
b1 8

#270000
0!
0#
1&
b1010101010101010101010101010101 '
b11111111111111111111111111111111 (
0,
0-
0/
12
b1010101010101010101010101010101 3
b11111111111111111111111111111111 4
b1111111111111111111111111111111110101010101010101010101010101011 5
b11111111111111111010101010101010 6
b11111111111111111010101010101010 7
b0 <

#275000
1!
b11111111111111111010101010101010 )
1-
b11111111111111110101010101010100 7
b11111111111111111010101010101010 :

#280000
0!
b10000100100001001101011000001001 '
b10110001111100000101011001100011 (
1,
0-
b10000100100001001101011000001001 3
b10110001111100000101011001100011 4
b10010110100111000101001101000011000000101101011100101101111011 5
b10100110100001100000010110101 6
b10100110100000110101101011111 7
b1 <

#285000
1!
b10100110100000110101101011111 )
1-
b101001101000010010110000010100 7
b10100110100000110101101011111 :

#290000
0!
b1000110110111111001100110001101 '
b10110010110000101000010001100101 (
0-
b1000110110111111001100110001101 3
b10110010110000101000010001100101 4
b1110101010011101101110010101000010101000001111100100100010100001 5
b10111001010100001010100000111110 6
b11001110001000010001001110011101 7
b10 <

#295000
1!
b11001110001000010001001110011101 )
1-
b10000111011100011011101111011011 7
b11001110001000010001001110011101 :

#300000
0!
b1010101010101010101010101010101 '
b11111111111111111111111111111111 (
0,
0-
b1010101010101010101010101010101 3
b11111111111111111111111111111111 4
b1111111111111111111111111111111110101010101010101010101010101011 5
b11111111111111111010101010101010 6
b11001110001000001011111001000111 7
b11 <

#305000
1!
b11001110001000001011111001000111 )
1-
b11001110001000000110100011110001 7
b11001110001000001011111001000111 :

#310000
0!
b110110101111100110100001101 '
b111011001000111111000101110110 (
1,
0-
b110110101111100110100001101 3
b111011001000111111000101110110 4
b110010100101100100011011101010111010010001100000011111110 5
b10110010001101110101011101001000 6
b10000000010110000001010110001111 7
b100 <

#315000
1!
b10000000010110000001010110001111 )
1-
b110010100011110110110011010111 7
b10000000010110000001010110001111 :

#320000
0!
b1110110110101000101011111101101 '
b1000110001011011111011110001100 (
0-
b1110110110101000101011111101101 3
b1000110001011011111011110001100 4
b10000010010011011001100100011000011111100111101100000010011100 5
b1100110010001100001111110011110 6
b11100110100111100011010100101101 7
b101 <

#325000
1!
b11100110100111100011010100101101 )
1-
b1001100111001000101010011001011 7
b11100110100111100011010100101101 :

#330000
0!
b11100011001101110010010011000110 '
b11100010111101111000010011000101 (
0-
b11100011001101110010010011000110 3
b11100010111101111000010011000101 4
b1101000011101101001111011110001111011011110110010001011110 5
b10110100111101111000111101101111 6
b10011011100101011100010010011100 7
b110 <

#335000
1!
b10011011100101011100010010011100 )
1-
b1010000100011010101010000001011 7
b10011011100101011100010010011100 :

#340000
0!
b1010101010101010101010101010101 '
b11111111111111111111111111111111 (
0,
0-
b1010101010101010101010101010101 3
b11111111111111111111111111111111 4
b1111111111111111111111111111111110101010101010101010101010101011 5
b11111111111111111010101010101010 6
b10011011100101010110111101000110 7
b111 <

#345000
1!
b10011011100101010110111101000110 )
1-
b10011011100101010001100111110000 7
b10011011100101010110111101000110 :

#350000
0!
b10111011110100100111001001110111 '
b10001001001100101101011000010010 (
1,
0-
b10111011110100100111001001110111 3
b10001001001100101101011000010010 4
b1111110100011101000101110001000101010101110011000011001011110 5
b10100010111000100010101010111001 6
b111110011101111001100111111111 7
b1000 <

#355000
1!
b111110011101111001100111111111 )
1-
b11100001010110011100010010111000 7
b111110011101111001100111111111 :

#360000
0!
b1111001001100000110100111110010 '
b11100111011101101001011011001110 (
0-
b1111001001100000110100111110010 3
b11100111011101101001011011001110 4
b1111010001100010011010010101110000010110100101010000110010111100 5
b1101001010111000001011010010101 6
b10100111110100111011000010010100 7
b1001 <

#365000
1!
b10100111110100111011000010010100 )
1-
b10001001011111100011100101001 7
b10100111110100111011000010010100 :

#370000
0!
b1010101010101010101010101010101 '
b11111111111111111111111111111111 (
0,
0-
b1010101010101010101010101010101 3
b11111111111111111111111111111111 4
b1111111111111111111111111111111110101010101010101010101010101011 5
b11111111111111111010101010101010 6
b10100111110100110101101100111110 7
b1010 <

#375000
1!
b10100111110100110101101100111110 )
1-
b10100111110100110000010111101000 7
b10100111110100110101101100111110 :

#380000
0!
b101110010110000100100101011100 '
b11011110100011100010100010111101 (
1,
0-
b101110010110000100100101011100 3
b11011110100011100010100010111101 4
b1111100111110010000000101001101001111011101011001000100011101100 5
b10100110100111101110101100 6
b10101010011011011101011011101010 7
b1011 <

#385000
1!
b10101010011011011101011011101010 )
1-
b10101101000010000101001010010110 7
b10101010011011011101011011101010 :

#390000
0!
b10110010101001110010011001100101 '
b10110001111011110110001001100011 (
0-
b10110010101001110010011001100101 3
b10110001111011110110001001100011 4
b1011110010110000101110111100111000000101000011000001100001111 5
b10111011110011100000010100001 6
b11000001111001111001011110001011 7
b1100 <

#395000
1!
b11000001111001111001011110001011 )
1-
b11011001011000010101100000101100 7
b11000001111001111001011110001011 :

#400000
0!
b1010101010101010101010101010101 '
b11111111111111111111111111111111 (
0,
0-
b1010101010101010101010101010101 3
b11111111111111111111111111111111 4
b1111111111111111111111111111111110101010101010101010101010101011 5
b11111111111111111010101010101010 6
b11000001111001110100001000110101 7
b1101 <

#405000
1!
b11000001111001110100001000110101 )
1-
b11000001111001101110110011011111 7
b11000001111001110100001000110101 :

#410000
0!
0-
b1110 <

#415000
1!
b11000001111001101110110011011111 )
1-
b11000001111001101001011110001001 7
b11000001111001101110110011011111 :

#420000
0!
0-
b1111 <

#425000
1!
b11000001111001101001011110001001 )
1-
b11000001111001100100001000110011 7
b11000001111001101001011110001001 :

#430000
0!
0-
b10000 <

#435000
1!
b11000001111001100100001000110011 )
1-
b11000001111001011110110011011101 7
b11000001111001100100001000110011 :

#440000
0!
b11001011001000000011111010010110 '
b10001001100000111011100000010011 (
1,
0-
b11001011001000000011111010010110 3
b10001001100000111011100000010011 4
b1100001111000110011100110001110001101001000100111010100100010 5
b11001110011000111000110100100010 6
b10010000010010011100111101010101 7
b10001 <

#445000
1!
b10010000010010011100111101010101 )
1-
b1011110101011010101110001110111 7
b10010000010010011100111101010101 :

#450000
0!
b10101001101001111101011001010011 '
b110101100111111101110101101011 (
0-
b10101001101001111101011001010011 3
b110101100111111101110101101011 4
b1110110111101001110100111110111100011001101110010011101110110001 5
b11010011111011110001100110111001 6
b1100100001110001110100100001110 7
b10010 <

#455000
1!
b1100100001110001110100100001110 )
1-
b111000001010000000001011000111 7
b1100100001110001110100100001110 :

#460000
0!
b10000001000101110100101000000010 '
b11010111010101100011111010101110 (
0-
b10000001000101110100101000000010 3
b11010111010101100011111010101110 4
b1010000101000100000111110010111101100011011001100100101011100 5
b10000011111001011110110001101100 6
b11101000000111101101010101111010 7
b10011 <

#465000
1!
b11101000000111101101010101111010 )
1-
b1101100000001001100000111100110 7
b11101000000111101101010101111010 :

#470000
0!
b11100111110001010111001011001111 '
b10001100001000100100100100011 (
0-
b11100111110001010111001011001111 3
b10001100001000100100100100011 4
b1111111001010111100101111000001011101111011101111011100101001101 5
b10010111100000101110111101110111 6
b1111111101000011100010011110001 7
b10100 <

#475000
1!
b1111111101000011100010011110001 )
1-
b10111001001001011010001101000 7
b1111111101000011100010011110001 :

#480000
0!
b1010101010101010101010101010101 '
b11111111111111111111111111111111 (
0,
0-
b1010101010101010101010101010101 3
b11111111111111111111111111111111 4
b1111111111111111111111111111111110101010101010101010101010101011 5
b11111111111111111010101010101010 6
b1111111101000010110111110011011 7
b10101 <

#485000
1!
b1111111101000010110111110011011 )
1-
b1111111101000010001101001000101 7
b1111111101000010110111110011011 :

#490000
0!
0-
b10110 <

#495000
1!
b1111111101000010001101001000101 )
1-
b1111111101000001100010011101111 7
b1111111101000010001101001000101 :

#500000
0!
0-
b10111 <

#505000
1!
b1111111101000001100010011101111 )
1-
b1111111101000000110111110011001 7
b1111111101000001100010011101111 :

#510000
0!
0-
b11000 <

#515000
1!
b1111111101000000110111110011001 )
1-
b1111111101000000001101001000011 7
b1111111101000000110111110011001 :

#520000
0!
0-
b11001 <

#525000
1!
b1111111101000000001101001000011 )
1-
b1111111100111111100010011101101 7
b1111111101000000001101001000011 :

#530000
0!
b11101100010010110011010011011000 '
b111100001000001111001101111000 (
1,
0-
b11101100010010110011010011011000 3
b111100001000001111001101111000 4
b1111101101011111000101110000101101100001011010011100110101000000 5
b10111000010110110000101101001 6
b10010110101010110111101110101100 7
b11010 <

#535000
1!
b10010110101010110111101110101100 )
1-
b10101101101101101101110100010101 7
b10010110101010110111101110101100 :

#540000
0!
b1110101110001010000110111101011 '
b1011011000000100110010110110110 (
0-
b1110101110001010000110111101011 3
b1011011000000100110010110110110 4
b10100111011110001001100100011100011101011010111001110000010010 5
b100110010001110001110101101011 6
b10111100111100101001100100010111 7
b11011 <

#545000
1!
b10111100111100101001100100010111 )
1-
b11100011001110011011011010000010 7
b10111100111100101001100100010111 :

#550000
0!
b1010101010101010101010101010101 '
b11111111111111111111111111111111 (
0,
0-
b1010101010101010101010101010101 3
b11111111111111111111111111111111 4
b1111111111111111111111111111111110101010101010101010101010101011 5
b11111111111111111010101010101010 6
b10111100111100100100001111000001 7
b11100 <

#555000
1!
b10111100111100100100001111000001 )
1-
b10111100111100011110111001101011 7
b10111100111100100100001111000001 :

#560000
0!
0-
b11101 <

#565000
1!
b10111100111100011110111001101011 )
1-
b10111100111100011001100100010101 7
b10111100111100011110111001101011 :

#570000
0!
0-
b11110 <

#575000
1!
b10111100111100011001100100010101 )
1-
b10111100111100010100001110111111 7
b10111100111100011001100100010101 :

#580000
0!
0-
b11111 <

#585000
1!
b10111100111100010100001110111111 )
1-
b10111100111100001110111001101001 7
b10111100111100010100001110111111 :

#590000
0!
b10111000100101111011111001110001 '
b1000010111100100100000110000101 (
1,
0-
b10111000100101111011111001110001 3
b1000010111100100100000110000101 4
b1110110101010011100011000100010010010111000000101010000110110101 5
b10001100010001001001011100000010 6
b1001001001101011101101011000001 7
b100000 <

#595000
1!
b1001001001101011101101011000001 )
1-
b11010101011110100111000111000011 7
b1001001001101011101101011000001 :

#600000
0!
b10011101110011000110000000111011 '
b11101000001100011001100111010 (
0-
b10011101110011000110000000111011 3
b11101000001100011001100111010 4
b1111010011011101110001100000101001100111110110111000111001011110 5
b11000110000010100110011111011011 6
b1111010000000100001010011100 7
b100001 <

#605000
1!
b1111010000000100001010011100 )
1-
b11010101010010101010101001110111 7
b1111010000000100001010011100 :

#610000
0!
b1010101010101010101010101010101 '
b11111111111111111111111111111111 (
0,
0-
b1010101010101010101010101010101 3
b11111111111111111111111111111111 4
b1111111111111111111111111111111110101010101010101010101010101011 5
b11111111111111111010101010101010 6
b1111001111111110110101000110 7
b100010 <

#615000
1!
b1111001111111110110101000110 )
1-
b1111001111111001011111110000 7
b1111001111111110110101000110 :

#620000
0!
b1111000110110011001101111110001 '
b1101100100111000100101111011001 (
1,
0-
b1111000110110011001101111110001 3
b1101100100111000100101111011001 4
b11001101000101100101100011001011100100000000001100101001001001 5
b10010110001100101110010000000000 6
b10100101011100101101000101000110 7
b100011 <

#625000
1!
b10100101011100101101000101000110 )
1-
b111011101001011011010101000110 7
b10100101011100101101000101000110 :

#630000
0!
b1010101010101010101010101010101 '
b11111111111111111111111111111111 (
0,
0-
b1010101010101010101010101010101 3
b11111111111111111111111111111111 4
b1111111111111111111111111111111110101010101010101010101010101011 5
b11111111111111111010101010101010 6
b10100101011100100111101111110000 7
b100100 <

#635000
1!
b10100101011100100111101111110000 )
1-
b10100101011100100010011010011010 7
b10100101011100100111101111110000 :

#640000
0!
0-
b100101 <

#645000
1!
b10100101011100100010011010011010 )
1-
b10100101011100011101000101000100 7
b10100101011100100010011010011010 :

#650000
0!
b1000111101110011010000110001111 '
b1111100011011011010100111111000 (
1,
0-
b1000111101110011010000110001111 3
b1111100011011011010100111111000 4
b10001011011100101000111110101000010101010111101110100110001000 5
b10100011111010100001010101011110 6
b1001001010111000011101111111000 7
b100110 <

#655000
1!
b1001001010111000011101111111000 )
1-
b11101101010001100101000101010110 7
b1001001010111000011101111111000 :

#660000
0!
b11001111110001000101011010011111 '
b10101110011111011001010001011100 (
0-
b11001111110001000101011010011111 3
b10101110011111011001010001011100 4
b111101011011011100110010101110001010010001100000110100100100 5
b1110011001010111000101001000110 6
b10111100100001111100011000111110 7
b100111 <

#665000
1!
b10111100100001111100011000111110 )
1-
b101111101100110101000010000100 7
b10111100100001111100011000111110 :

#670000
0!
b1000100110111100011011110001001 '
b10100100101011100011001001001001 (
0-
b1000100110111100011011110001001 3
b10100100101011100011001001001001 4
b1110011101101111000000001001101110001101010101001001100000010001 5
b100110111000110101010100 6
b10111101001000110101001110010010 7
b101000 <

#675000
1!
b10111101001000110101001110010010 )
1-
b10111101101111101110000011100110 7
b10111101001000110101001110010010 :

#680000
0!
b1010101010101010101010101010101 '
b11111111111111111111111111111111 (
0,
0-
b1010101010101010101010101010101 3
b11111111111111111111111111111111 4
b1111111111111111111111111111111110101010101010101010101010101011 5
b11111111111111111010101010101010 6
b10111101001000101111111000111100 7
b101001 <

#685000
1!
b10111101001000101111111000111100 )
1-
b10111101001000101010100011100110 7
b10111101001000101111111000111100 :

#690000
0!
b10101000110001111111110001010001 '
b1001011001000010010111110010110 (
1,
0-
b10101000110001111111110001010001 3
b1001011001000010010111110010110 4
b1110011001100111010010000111110011011101111100011011011001110110 5
b1001000011111001101110111110001 6
b101100111111101110000101101 7
b101010 <

#695000
1!
b101100111111101110000101101 )
1-
b1001110000111001011101000011110 7
b101100111111101110000101101 :

#700000
0!
b1010101010101010101010101010101 '
b11111111111111111111111111111111 (
0,
0-
b1010101010101010101010101010101 3
b11111111111111111111111111111111 4
b1111111111111111111111111111111110101010101010101010101010101011 5
b11111111111111111010101010101010 6
b101100111111000011011010111 7
b101011 <

#705000
1!
b101100111111000011011010111 )
1-
b101100111110011000110000001 7
b101100111111000011011010111 :

#710000
0!
0-
b101100 <

#715000
1!
b101100111110011000110000001 )
1-
b101100111101101110000101011 7
b101100111110011000110000001 :

#720000
0!
0-
b101101 <

#725000
1!
b101100111101101110000101011 )
1-
b101100111101000011011010101 7
b101100111101101110000101011 :

#730000
0!
b11110111100101110110100111101 '
b1001000011001101101100010010 (
1,
0-
b11110111100101110110100111101 3
b1001000011001101101100010010 4
b100011000000110000011011001000001111000111101110101001010 5
b11000001101100100000111100011 6
b11101110101010001111000001110 7
b101110 <

#735000
1!
b11101110101010001111000001110 )
1-
b110110000010110101111111110001 7
b11101110101010001111000001110 :

#740000
0!
b1010101010101010101010101010101 '
b11111111111111111111111111111111 (
0,
0-
b1010101010101010101010101010101 3
b11111111111111111111111111111111 4
b1111111111111111111111111111111110101010101010101010101010101011 5
b11111111111111111010101010101010 6
b11101110101001100100010111000 7
b101111 <

#745000
1!
b11101110101001100100010111000 )
1-
b11101110101000111001101100010 7
b11101110101001100100010111000 :

#750000
0!
b11100110110011110011100111001 '
b1111110100101000111100011111 (
1,
0-
b11100110110011110011100111001 3
b1111110100101000111100011111 4
b111001000011111110110110100111010010011011101011011100111 5
b1111111011011010011101001001101 6
b10011101010000100000001100000101 7
b110000 <

#755000
1!
b10011101010000100000001100000101 )
1-
b11100101011110011110101010010 7
b10011101010000100000001100000101 :

#760000
0!
b1000010110110010010111110000101 '
b10111100000101001000100001111000 (
0-
b1000010110110010010111110000101 3
b10111100000101001000100001111000 4
b1110111001000011101010111111101100011001011100001110111001011000 5
b10101011111110110001100101110000 6
b1001001001111010001110001110101 7
b110001 <

#765000
1!
b1001001001111010001110001110101 )
1-
b11110101001110000011010111100101 7
b1001001001111010001110001110101 :

#770000
0!
b100100100010110100101101001001 '
b10011111111100101010111000111111 (
0-
b100100100010110100101101001001 3
b10011111111100101010111000111111 4
b1111001001001001110111010000011000101101011101010010010011110111 5
b11011101000001100010110101110101 6
b100110010000110100100111101010 7
b110010 <

#775000
1!
b100110010000110100100111101010 )
1-
b11010010010111011101011111 7
b100110010000110100100111101010 :

#780000
0!
b1010101010101010101010101010101 '
b11111111111111111111111111111111 (
0,
0-
b1010101010101010101010101010101 3
b11111111111111111111111111111111 4
b1111111111111111111111111111111110101010101010101010101010101011 5
b11111111111111111010101010101010 6
b100110010000101111010010010100 7
b110011 <

#785000
1!
b100110010000101111010010010100 )
1-
b100110010000101001111100111110 7
b100110010000101111010010010100 :

#790000
0!
0-
b110100 <

#795000
1!
b100110010000101001111100111110 )
1-
b100110010000100100100111101000 7
b100110010000101001111100111110 :

#800000
0!
0-
b110101 <

#805000
1!
b100110010000100100100111101000 )
1-
b100110010000011111010010010010 7
b100110010000100100100111101000 :

#810000
0!
0-
b110110 <

#815000
1!
b100110010000011111010010010010 )
1-
b100110010000011001111100111100 7
b100110010000011111010010010010 :

#820000
0!
0-
b110111 <

#825000
1!
b100110010000011001111100111100 )
1-
b100110010000010100100111100110 7
b100110010000011001111100111100 :

#830000
0!
0-
b111000 <

#835000
1!
b100110010000010100100111100110 )
1-
b100110010000001111010010010000 7
b100110010000010100100111100110 :

#840000
0!
0-
b111001 <

#845000
1!
b100110010000001111010010010000 )
1-
b100110010000001001111100111010 7
b100110010000001111010010010000 :

#850000
0!
b11010001100010111011010010100011 '
b10010111100110011010100000101111 (
1,
0-
b11010001100010111011010010100011 3
b10010111100110011010100000101111 4
b1001011110001110100001110001101000001100111000010000111101101 5
b11010000111000110100000110011100 6
b11110111001001000011011000101100 7
b111010 <

#855000
1!
b11110111001001000011011000101100 )
1-
b11001000000001110111011111001000 7
b11110111001001000011011000101100 :

#860000
0!
b10101111110110000101011001011111 '
b100010001010010000110101000100 (
0-
b10101111110110000101011001011111 3
b100010001010010000110101000100 4
b1111010101001101111000001111011100100101000100001100010000111100 5
b11100000111101110010010100010000 6
b11011000000110110101101100111100 7
b111011 <

#865000
1!
b11011000000110110101101100111100 )
1-
b10111001000100101000000001001100 7
b11011000000110110101101100111100 :

#870000
0!
b11100101100110110011011011001011 '
b11110011000010010001101011100110 (
0-
b11100101100110110011011011001011 3
b11110011000010010001101011100110 4
b101010110001011011110011010101011001001101101100001100010 5
b101101111001101010101100100110 6
b110000000100000011001100010 7
b111100 <

#875000
1!
b110000000100000011001100010 )
1-
b110011111010001011000110001000 7
b110000000100000011001100010 :

#880000
0!
b1010101010101010101010101010101 '
b11111111111111111111111111111111 (
0,
0-
b1010101010101010101010101010101 3
b11111111111111111111111111111111 4
b1111111111111111111111111111111110101010101010101010101010101011 5
b11111111111111111010101010101010 6
b110000000011011000100001100 7
b111101 <

#885000
1!
b110000000011011000100001100 )
1-
b110000000010101101110110110 7
b110000000011011000100001100 :

#890000
0!
b11110110100000101110001011101101 '
b11101101010100110110110011011010 (
1,
0-
b11110110100000101110001011101101 3
b11101101010100110110110011011010 4
b10110001001100011000111100011111000010000011100111010010 5
b110001100011110001111100001000 6
b110111100100001101000000010100 7
b111110 <

#895000
1!
b110111100100001101000000010100 )
1-
b1101001000111111110111100011100 7
b110111100100001101000000010100 :

#900000
0!
b11011010100010101110001010110101 '
b11101111101111101001010011011111 (
0-
b11011010100010101110001010110101 3
b11101111101111101001010011011111 4
b1001100000111001000011110111100111011000100001111110101011 5
b11100100001111011110011101100010 6
b11011110011101011011101110110 7
b111111 <

#905000
1!
b11011110011101011011101110110 )
1-
b11001001111011011000 7
b11011110011101011011101110110 :

#910000
0!
b100010001100011111111101000100 '
b11101000011101000000110011010000 (
0-
b100010001100011111111101000100 3
b11101000011101000000110011010000 4
b1111110011011010110100000110111101101011011001101001011101000000 5
b11010000011011110110101101100110 6
b11101100001111100010001011011100 7
b1000000 <

#915000
1!
b11101100001111100010001011011100 )
1-
b10111100101011011000111001000010 7
b11101100001111100010001011011100 :

#920000
0!
b1010101010101010101010101010101 '
b11111111111111111111111111111111 (
0,
0-
b1010101010101010101010101010101 3
b11111111111111111111111111111111 4
b1111111111111111111111111111111110101010101010101010101010101011 5
b11111111111111111010101010101010 6
b11101100001111011100110110000110 7
b1000001 <

